Metadata-Version: 2.1
Name: djangoshop-shopit
Version: 0.4.2
Summary: Fully featured shop application built on djangoSHOP framework.
Home-page: https://github.com/dinoperovic/djangoshop-shopit
Author: Dino Perovic
Author-email: dino.perovic@gmail.com
License: BSD License
Platform: OS Independent
Classifier: Environment :: Web Environment
Classifier: Framework :: Django :: 1.10
Classifier: Framework :: Django :: 1.11
Classifier: Framework :: Django
Classifier: Intended Audience :: Developers
Classifier: License :: OSI Approved :: BSD License
Classifier: Operating System :: OS Independent
Classifier: Programming Language :: Python :: 2.7
Classifier: Programming Language :: Python :: 3.4
Classifier: Programming Language :: Python :: 3.5
Requires-Dist: django-shop (>=0.12)
Requires-Dist: django-cms (>=3.5.0)
Requires-Dist: django-parler (>=1.6.5)
Requires-Dist: django-mptt (>=0.8.6)
Requires-Dist: django-admin-sortable2 (>=0.6.4)
Requires-Dist: django-measurement (>=2.4.0)
Requires-Dist: django-phonenumber-field (>=1.3.0)
